pyvisjs/__init__.py
pyvisjs/_version.py
pyvisjs/base_dictable.py
pyvisjs/edge.py
pyvisjs/network.py
pyvisjs/node.py
pyvisjs/options.py
pyvisjs/utils.py
pyvisjs/templates/base-template.html
pyvisjs/templates/basic-template.html
pyvisjs/templates/container-template.html
pyvisjs/templates/create_network.js
pyvisjs/templates/data-table-bottom.html
pyvisjs/templates/data-table-left.html
pyvisjs/templates/data-table-right.html
pyvisjs/templates/draw_title.js
pyvisjs/templates/enable_startAnimation.js
pyvisjs/templates/functions.js
pyvisjs/templates/init_dataTables.js
pyvisjs/templates/init_sankey.js
pyvisjs/templates/init_tomSelect.js
pyvisjs/templates/select-edge-filter.html
pyvisjs-1.0.0b11.dist-info/LICENSE
pyvisjs-1.0.0b11.dist-info/METADATA
pyvisjs-1.0.0b11.dist-info/WHEEL
pyvisjs-1.0.0b11.dist-info/top_level.txt
pyvisjs-1.0.0b11.dist-info/RECORD
