Metadata-Version: 2.1
Name: pyvisjs
Version: 1.0.0b11
Summary: A Python wrapper for vis.js Network
Author-email: Andrey Morozov <andrey@morozov.lv>
License: MIT License
Project-URL: Homepage, https://gitlab.com/22kittens/pyvisjs
Project-URL: Repository, https://gitlab.com/22kittens/pyvisjs.git
Project-URL: Issues, https://gitlab.com/22kittens/pyvisjs/-/issues
Keywords: visjs,visNetwork,graph,network
Classifier: Programming Language :: Python
Requires-Python: >=3.9
License-File: LICENSE
Requires-Dist: Jinja2
Provides-Extra: all
Requires-Dist: pyvisjs[test] ; extra == 'all'
Provides-Extra: test
Requires-Dist: pytest ; extra == 'test'
Requires-Dist: pytest-cov ; extra == 'test'
